{
  "Brock Burke": 656271,
  "Christian Moore": 695681,
  "Connor Brogdon": 641401,
  "Gustavo Campero": 672569,
  "H\u00e9ctor Neris": 593576,
  "Hunter Strickland": 519326,
  "Jack Kochanowicz": 686799,
  "Jo Adell": 666176,
  "Jos\u00e9 Soriano": 667755,
  "Kenley Jansen": 445276,
  "Kyle Hendricks": 543294,
  "Kyren Paris": 677347,
  "LaMonte Wade Jr.": 664774,
  "Logan O'Hoppe": 681351,
  "Luis Rengifo": 650859,
  "Mike Trout": 545361,
  "Nolan Schanuel": 694384,
  "Reid Detmers": 672282,
  "Ryan Zeferjahn": 666171,
  "Sam Bachman": 696147,
  "Scott Kingery": 664068,
  "Taylor Ward": 621493,
  "Travis d'Arnaud": 518595,
  "Tyler Anderson": 542881,
  "Yusei Kikuchi": 579328,
  "Zach Neto": 687263,
  "Alek Thomas": 677950,
  "Anthony DeSclafani": 543101,
  "Brandon Pfaadt": 694297,
  "Eduardo Rodriguez": 593958,
  "Eugenio Su\u00e1rez": 553993,
  "Geraldo Perdomo": 672695,
  "Ildemaro Vargas": 545121,
  "Jake McCarthy": 664983,
  "Jalen Beeks": 656222,
  "James McCann": 543510,
  "Jose Herrera": 645444,
  "Josh Naylor": 647304,
  "Juan Morillo": 666661,
  "Ketel Marte": 606466,
  "Kevin Ginkel": 656464,
  "Kyle Backhus": 679775,
  "Lourdes Gurriel Jr.": 666971,
  "Merrill Kelly": 518876,
  "Pavin Smith": 656976,
  "Randal Grichuk": 545341,
  "Ryan Thompson": 657044,
  "Ryne Nelson": 669194,
  "Shelby Miller": 571946,
  "Tayler Scott": 605463,
  "Tim Tawa": 694374,
  "Zac Gallen": 668678,
  "Andrew Kittredge": 552640,
  "Bryan Baker": 641329,
  "Cedric Mullins": 656775,
  "Chadwick Tromp": 644433,
  "Charlie Morton": 450203,
  "Coby Mayo": 691723,
  "Colton Cowser": 681297,
  "Dean Kremer": 665152,
  "Dylan Carlson": 666185,
  "F\u00e9lix Bautista": 642585,
  "Gary S\u00e1nchez": 596142,
  "Gregory Soto": 642397,
  "Gunnar Henderson": 683002,
  "Jackson Holliday": 702616,
  "Jordan Westburg": 676059,
  "Keegan Akin": 669211,
  "Luis V\u00e1zquez": 676679,
  "Ram\u00f3n Laureano": 657656,
  "Ram\u00f3n Ur\u00edas": 602104,
  "Ryan O'Hearn": 656811,
  "Scott Blewett": 656240,
  "Seranthony Dom\u00ednguez": 622554,
  "Tomoyuki Sugano": 608372,
  "Trevor Rogers": 669432,
  "Yaramil Hiraldo": 682274,
  "Zach Eflin": 621107,
  "Abraham Toro": 647351,
  "Aroldis Chapman": 547973,
  "Brayan Bello": 678394,
  "Brennan Bernardino": 657514,
  "Carlos Narv\u00e1ez": 665966,
  "Ceddanne Rafaela": 678882,
  "Connor Wong": 657136,
  "David Hamilton": 666152,
  "Garrett Crochet": 676979,
  "Garrett Whitlock": 676477,
  "Greg Weissert": 669711,
  "Jarren Duran": 680776,
  "Jorge Alcala": 660896,
  "Justin Wilson": 458677,
  "Lucas Giolito": 608337,
  "Luis Guerrero": 692285,
  "Marcelo Mayer": 691785,
  "Nate Eaton": 681987,
  "Richard Fitts": 690916,
  "Rob Refsnyder": 608701,
  "Roman Anthony": 701350,
  "Romy Gonzalez": 663853,
  "Trevor Story": 596115,
  "Walker Buehler": 621111,
  "Wilyer Abreu": 677800,
  "Zack Kelly": 677161,
  "Brad Keller": 641745,
  "Cade Horton": 690990,
  "Caleb Thielbar": 573204,
  "Carson Kelly": 608348,
  "Chris Flexen": 623167,
  "Colin Rea": 607067,
  "Daniel Palencia": 694037,
  "Dansby Swanson": 621020,
  "Drew Pomeranz": 519141,
  "Ian Happ": 664023,
  "Jameson Taillon": 592791,
  "Jon Berti": 542932,
  "Justin Turner": 457759,
  "Kyle Tucker": 663656,
  "Matt Shaw": 807713,
  "Matthew Boyd": 571510,
  "Michael Busch": 683737,
  "Michael Fulmer": 605242,
  "Nico Hoerner": 663538,
  "Pete Crow-Armstrong": 691718,
  "Porter Hodge": 687863,
  "Reese McGuire": 624512,
  "Ryan Brasier": 518489,
  "Ryan Pressly": 519151,
  "Seiya Suzuki": 673548,
  "Vidal Bruj\u00e1n": 660644,
  "Andrew Abbott": 671096,
  "Brady Singer": 663903,
  "Brent Suter": 608718,
  "Chase Burns": 695505,
  "Christian Encarnacion-Strand": 687952,
  "Connor Joe": 656582,
  "Connor Phillips": 683175,
  "Elly De La Cruz": 682829,
  "Emilio Pag\u00e1n": 641941,
  "Gavin Lux": 666158,
  "Ian Gibaut": 664139,
  "Jake Fraley": 641584,
  "Jose Trevino": 624431,
  "Lyon Richardson": 680689,
  "Matt McLain": 680574,
  "Nick Lodolo": 666157,
  "Nick Martinez": 607259,
  "Rece Hinds": 677956,
  "Santiago Espinal": 669289,
  "Scott Barlow": 605130,
  "Spencer Steer": 668715,
  "TJ Friedl": 670770,
  "Taylor Rogers": 573124,
  "Tony Santillan": 663574,
  "Tyler Stephenson": 663886,
  "Will Benson": 666181,
  "Angel Mart\u00ednez": 682657,
  "Austin Hedges": 595978,
  "Bo Naylor": 666310,
  "Cade Smith": 671922,
  "Carlos Santana": 467793,
  "Daniel Schneemann": 682177,
  "David Fry": 681807,
  "Emmanuel Clase": 661403,
  "Gabriel Arias": 672356,
  "Gavin Williams": 668909,
  "Hunter Gaddis": 683769,
  "Jakob Junis": 596001,
  "Johnathan Rodr\u00edguez": 671286,
  "Jos\u00e9 Ram\u00edrez": 608070,
  "Kolby Allard": 663465,
  "Kyle Manzardo": 700932,
  "Lane Thomas": 657041,
  "Logan Allen": 671106,
  "Luis L. Ortiz": 682847,
  "Matt Festa": 670036,
  "Nic Enright": 663671,
  "Nolan Jones": 666134,
  "Slade Cecconi": 677944,
  "Steven Kwan": 680757,
  "Tanner Bibee": 676440,
  "Tim Herrin": 682120,
  "Angel Chivilli": 683409,
  "Anthony Molina": 683627,
  "Antonio Senzatela": 622608,
  "Austin Gomber": 596295,
  "Braxton Fulford": 690924,
  "Brenton Doyle": 686668,
  "Chase Dollander": 801403,
  "Germ\u00e1n M\u00e1rquez": 608566,
  "Hunter Goodman": 696100,
  "Jake Bird": 656234,
  "Jimmy Herget": 623474,
  "Jordan Beck": 687597,
  "Juan Mejia": 675848,
  "Kyle Farmer": 571657,
  "Michael Toglia": 669911,
  "Mickey Moniak": 666160,
  "Orlando Arcia": 606115,
  "Ryan McMahon": 641857,
  "Ryan Ritter": 690022,
  "Ryan Rolison": 669020,
  "Sam Hilliard": 656541,
  "Seth Halvorsen": 678020,
  "Thairo Estrada": 642731,
  "Tyler Freeman": 671289,
  "Tyler Kinley": 641755,
  "Victor Vodnik": 680767,
  "Brant Hurter": 676428,
  "Brenan Hanifee": 669724,
  "Carlos Hern\u00e1ndez": 672578,
  "Casey Mize": 663554,
  "Chase Lee": 695445,
  "Colt Keith": 690993,
  "Dillon Dingler": 693307,
  "Dylan Smith": 681916,
  "Gleyber Torres": 650402,
  "Jack Flaherty": 656427,
  "Jahmai Jones": 663330,
  "Jake Rogers": 668670,
  "Javier B\u00e1ez": 595879,
  "Kerry Carpenter": 681481,
  "Matt Gage": 657424,
  "Parker Meadows": 678009,
  "Riley Greene": 682985,
  "Sawyer Gipson-Long": 687830,
  "Spencer Torkelson": 679529,
  "Tarik Skubal": 669373,
  "Tommy Kahnle": 592454,
  "Trey Sweeney": 700242,
  "Tyler Holton": 663947,
  "Wenceel P\u00e9rez": 672761,
  "Will Vest": 676684,
  "Zach McKinstry": 656716,
  "Bennett Sousa": 656986,
  "Brandon Walter": 687888,
  "Bryan Abreu": 650556,
  "Bryan King": 687911,
  "Cam Smith": 701358,
  "C\u00e9sar Salazar": 663967,
  "Christian Walker": 572233,
  "Colton Gordon": 676467,
  "Cooper Hummel": 669450,
  "Framber Valdez": 664285,
  "Hunter Brown": 686613,
  "Isaac Paredes": 670623,
  "Jake Meyers": 676694,
  "Jeremy Pe\u00f1a": 665161,
  "Jordan Weems": 607179,
  "Jose Altuve": 514888,
  "Josh Hader": 623352,
  "Kaleb Ort": 672391,
  "Luis Guillorme": 641645,
  "Mauricio Dub\u00f3n": 643289,
  "Nick Hernandez": 663321,
  "Ryan Gusto": 687473,
  "Steven Okert": 595345,
  "Taylor Trammell": 666211,
  "Victor Caratini": 605170,
  "Yainer Diaz": 673237,
  "Angel Zerpa": 672582,
  "Bobby Witt Jr.": 677951,
  "Carlos Est\u00e9vez": 608032,
  "Daniel Lynch IV": 663738,
  "Drew Waters": 671221,
  "Freddy Fermin": 666023,
  "Jac Caglianone": 695506,
  "John Rave": 670231,
  "John Schreiber": 670167,
  "Jonathan India": 663697,
  "Kris Bubic": 663460,
  "Kyle Isbel": 664728,
  "Lucas Erceg": 668674,
  "Maikel Garcia": 672580,
  "Mark Canha": 592192,
  "Michael Lorenzen": 547179,
  "Michael Wacha": 608379,
  "Nick Loftin": 679845,
  "Noah Cameron": 702070,
  "Salvador Perez": 521692,
  "Sam Long": 669674,
  "Seth Lugo": 607625,
  "Steven Cruz": 674444,
  "Taylor Clarke": 664199,
  "Tyler Tolbert": 686475,
  "Vinnie Pasquantino": 686469,
  "Alex Vesia": 681911,
  "Andy Pages": 681624,
  "Anthony Banda": 607455,
  "Ben Casparius": 676508,
  "Clayton Kershaw": 477132,
  "Dalton Rushing": 687221,
  "Dustin May": 669160,
  "Enrique Hern\u00e1ndez": 571771,
  "Freddie Freeman": 518692,
  "Hyeseong Kim": 808975,
  "Jack Dreyer": 676263,
  "Justin Wrobleski": 680736,
  "Kirby Yates": 489446,
  "Lou Trivino": 642152,
  "Max Muncy": 691777,
  "Michael Conforto": 624424,
  "Michael Kopech": 656629,
  "Miguel Rojas": 500743,
  "Mookie Betts": 605141,
  "Shohei Ohtani": 660271,
  "Tanner Scott": 656945,
  "Teoscar Hern\u00e1ndez": 606192,
  "Tommy Edman": 669242,
  "Will Klein": 694361,
  "Will Smith": 669257,
  "Yoshinobu Yamamoto": 808967,
  "Alex Call": 669743,
  "Amed Rosario": 642708,
  "Andr\u00e9s Chaparro": 665953,
  "Brad Lord": 695418,
  "Brady House": 691781,
  "CJ Abrams": 682928,
  "Cole Henry": 669371,
  "Daylen Lile": 695734,
  "Drew Millas": 686452,
  "Eduardo Salazar": 674285,
  "Jackson Rutledge": 671131,
  "Jacob Young": 696285,
  "Jake Irvin": 663623,
  "James Wood": 695578,
  "Jose A. Ferrer": 678606,
  "Josh Bell": 605137,
  "Kyle Finnegan": 640448,
  "Luis Garc\u00eda Jr.": 671277,
  "MacKenzie Gore": 669022,
  "Michael Soroka": 647336,
  "Mitchell Parker": 680730,
  "Nathaniel Lowe": 663993,
  "Riley Adams": 656180,
  "Ryan Loutos": 702795,
  "Trevor Williams": 592866,
  "Zach Brzykcy": 694350,
  "Brandon Nimmo": 607043,
  "Brett Baty": 683146,
  "Clay Holmes": 605280,
  "David Peterson": 656849,
  "Dedniel N\u00fa\u00f1ez": 673380,
  "Edwin D\u00edaz": 621242,
  "Francisco Lindor": 596019,
  "Frankie Montas": 593423,
  "Griffin Canning": 656288,
  "Hayden Senger": 663584,
  "Huascar Brazob\u00e1n": 623211,
  "Jared Young": 676724,
  "Jeff McNeil": 643446,
  "Jos\u00e9 Butt\u00f3": 676130,
  "Jos\u00e9 Castillo": 620454,
  "Juan Soto": 665742,
  "Luis Torrens": 620443,
  "Paul Blackburn": 621112,
  "Pete Alonso": 624413,
  "Reed Garrett": 657585,
  "Richard Lovelady": 663992,
  "Ronny Mauricio": 677595,
  "Ryne Stanek": 592773,
  "Starling Marte": 516782,
  "Travis Jankowski": 608671,
  "Tyrone Taylor": 621438,
  "Austin Wynns": 642851,
  "Brent Rooker": 667670,
  "Denzel Clarke": 672016,
  "Gio Urshela": 570482,
  "Hogan Harris": 663687,
  "J.T. Ginn": 669372,
  "JJ Bleday": 668709,
  "JP Sears": 676664,
  "Jack Perkins": 678022,
  "Jacob Lopez": 682052,
  "Jacob Wilson": 805779,
  "Jeffrey Springs": 605488,
  "Lawrence Butler": 671732,
  "Luis Severino": 622663,
  "Luis Ur\u00edas": 649966,
  "Mason Miller": 695243,
  "Max Schuemann": 680474,
  "Michael Kelly": 547184,
  "Mitch Spence": 687765,
  "Nick Kurtz": 701762,
  "Sean Newcomb": 656794,
  "T.J. McFarland": 519008,
  "Tyler Ferguson": 621053,
  "Tyler Soderstrom": 691016,
  "Willie MacIver": 680862,
  "Adam Frazier": 624428,
  "Alexander Canario": 672744,
  "Andrew Heaney": 571760,
  "Andrew McCutchen": 457705,
  "Bailey Falter": 663559,
  "Braxton Ashcraft": 677952,
  "Bryan Reynolds": 668804,
  "Caleb Ferguson": 657571,
  "Carmen Mlodzinski": 669387,
  "Chase Shugart": 663767,
  "David Bednar": 670280,
  "Dennis Santana": 642701,
  "Henry Davis": 680779,
  "Isaac Mattson": 676755,
  "Isiah Kiner-Falefa": 643396,
  "Jared Triolo": 669707,
  "Joey Bart": 663698,
  "Ke'Bryan Hayes": 663647,
  "Michael Darrell-Hicks": 690382,
  "Mike Burrows": 681347,
  "Mitch Keller": 656605,
  "Nick Gonzales": 693304,
  "Oneil Cruz": 665833,
  "Paul Skenes": 694973,
  "Spencer Horwitz": 687462,
  "Tommy Pham": 502054,
  "Adrian Morejon": 670970,
  "Bryan Hoeing": 663773,
  "Bryce Johnson": 669369,
  "David Morgan": 688158,
  "Dylan Cease": 656302,
  "Elias D\u00edaz": 553869,
  "Fernando Tatis Jr.": 665487,
  "Gavin Sheets": 657757,
  "Jackson Merrill": 701538,
  "Jake Cronenworth": 630105,
  "Jason Adam": 592094,
  "Jeremiah Estrada": 669093,
  "Jose Iglesias": 578428,
  "Luis Arraez": 650333,
  "Manny Machado": 592518,
  "Mart\u00edn Maldonado": 455117,
  "Nick Pivetta": 601713,
  "Randy V\u00e1squez": 681190,
  "Robert Suarez": 663158,
  "Ryan Bergert": 686701,
  "Stephen Kolek": 663568,
  "Trenton Brooks": 670092,
  "Tyler Wade": 642180,
  "Wandy Peralta": 593974,
  "Xander Bogaerts": 593428,
  "Yuki Matsui": 673513,
  "Andr\u00e9s Mu\u00f1oz": 662253,
  "Ben Williamson": 810938,
  "Bryan Woo": 693433,
  "Cal Raleigh": 663728,
  "Carlos Vargas": 672841,
  "Casey Legumina": 668984,
  "Cole Young": 702284,
  "Dominic Canzone": 686527,
  "Donovan Solano": 456781,
  "Dylan Moore": 664238,
  "Eduard Bazardo": 660825,
  "Emerson Hancock": 676106,
  "Gabe Speier": 642100,
  "George Kirby": 669923,
  "J.P. Crawford": 641487,
  "Jorge Polanco": 593871,
  "Julio Rodr\u00edguez": 677594,
  "Logan Gilbert": 669302,
  "Luis Castillo": 622491,
  "Luke Raley": 670042,
  "Matt Brash": 666374,
  "Miles Mastrobuoni": 670156,
  "Mitch Garver": 641598,
  "Randy Arozarena": 668227,
  "Trent Thornton": 663423,
  "Zach Pop": 647315,
  "Andrew Knizner": 668800,
  "Brett Wisely": 689172,
  "Camilo Doval": 666808,
  "Casey Schmitt": 669477,
  "Christian Koss": 683766,
  "Daniel Johnson": 669288,
  "Dominic Smith": 642086,
  "Erik Miller": 669062,
  "Hayden Birdsong": 806185,
  "Heliot Ramos": 671218,
  "Joey Lucchesi": 664192,
  "Jung Hoo Lee": 808982,
  "Justin Verlander": 434378,
  "Landen Roupp": 694738,
  "Logan Webb": 657277,
  "Mike Yastrzemski": 573262,
  "Patrick Bailey": 672275,
  "Rafael Devers": 646240,
  "Randy Rodr\u00edguez": 678495,
  "Robbie Ray": 592662,
  "Ryan Walker": 676254,
  "Sean Hjelle": 663546,
  "Spencer Bivens": 702352,
  "Tyler Rogers": 643511,
  "Willy Adames": 642715,
  "Wilmer Flores": 527038,
  "Alec Burleson": 676475,
  "Andre Pallante": 669467,
  "Brendan Donovan": 680977,
  "Erick Fedde": 607200,
  "Garrett Hampson": 641658,
  "JoJo Romero": 668941,
  "John King": 667463,
  "Jordan Walker": 691023,
  "Kyle Leahy": 681517,
  "Lars Nootbaar": 663457,
  "Masyn Winn": 691026,
  "Matthew Liberatore": 669461,
  "Michael McGreevy": 700241,
  "Miles Mikolas": 571945,
  "Nolan Arenado": 571448,
  "Nolan Gorman": 669357,
  "Pedro Pag\u00e9s": 686780,
  "Phil Maton": 664208,
  "Riley O'Brien": 676617,
  "Ryan Helsley": 664854,
  "Sonny Gray": 543243,
  "Steven Matz": 571927,
  "Thomas Saggese": 695336,
  "Victor Scott II": 687363,
  "Willson Contreras": 575929,
  "Yohel Pozo": 650968,
  "Brandon Lowe": 664040,
  "Chandler Simpson": 802415,
  "Christopher Morel": 666624,
  "Curtis Mead": 678554,
  "Danny Jansen": 643376,
  "Drew Rasmussen": 656876,
  "Edwin Uceta": 670955,
  "Eric Orze": 679358,
  "Forrest Whitley": 666215,
  "Garrett Cleavinger": 664076,
  "Jake Mangum": 663968,
  "Jonathan Aranda": 666018,
  "Jos\u00e9 Caballero": 676609,
  "Josh Lowe": 666139,
  "Junior Caminero": 691406,
  "Kevin Kelly": 687330,
  "Mason Montgomery": 682254,
  "Matt Thaiss": 642136,
  "Paul Gervase": 801434,
  "Pete Fairbanks": 664126,
  "Ryan Pepiot": 686752,
  "Shane Baz": 669358,
  "Taj Bradley": 671737,
  "Taylor Walls": 670764,
  "Yandy D\u00edaz": 650490,
  "Zack Littell": 641793,
  "Adolis Garc\u00eda": 666969,
  "Alejandro Osuna": 696030,
  "Chris Martin": 455119,
  "Cole Winn": 668390,
  "Corey Seager": 608369,
  "Dane Dunning": 641540,
  "Evan Carter": 694497,
  "Ezequiel Duran": 677649,
  "Hoby Milner": 571948,
  "Jack Leiter": 683004,
  "Jacob Latz": 656641,
  "Jacob Webb": 657097,
  "Jacob deGrom": 594798,
  "Jonah Heim": 641680,
  "Josh Jung": 673962,
  "Josh Smith": 669701,
  "Justin Foscue": 679822,
  "Kumar Rocker": 677958,
  "Kyle Higashioka": 543309,
  "Luke Jackson": 592426,
  "Marcus Semien": 543760,
  "Patrick Corbin": 571578,
  "Robert Garcia": 676395,
  "Sam Haggerty": 664059,
  "Shawn Armstrong": 542888,
  "Wyatt Langford": 694671,
  "Addison Barger": 680718,
  "Alan Roden": 702176,
  "Alejandro Kirk": 672386,
  "Andr\u00e9s Gim\u00e9nez": 665926,
  "Bo Bichette": 666182,
  "Braydon Fisher": 680755,
  "Brendon Little": 663893,
  "Chad Green": 643338,
  "Chris Bassitt": 605135,
  "Davis Schneider": 676914,
  "Eric Lauer": 641778,
  "Ernie Clement": 676391,
  "George Springer": 543807,
  "Jeff Hoffman": 656546,
  "Jonatan Clase": 682729,
  "Jos\u00e9 Berr\u00edos": 621244,
  "Kevin Gausman": 592332,
  "Mason Fluharty": 689254,
  "Myles Straw": 664702,
  "Nathan Lukes": 664770,
  "Nick Sandlin": 680704,
  "Paxton Schultz": 687606,
  "Spencer Turnbull": 605513,
  "Tyler Heineman": 623168,
  "Vladimir Guerrero Jr.": 665489,
  "Yariel Rodr\u00edguez": 684320,
  "Bailey Ober": 641927,
  "Brock Stewart": 592779,
  "Brooks Lee": 686797,
  "Byron Buxton": 621439,
  "Carlos Correa": 621043,
  "Chris Paddack": 663978,
  "Christian V\u00e1zquez": 543877,
  "Cole Sands": 663485,
  "DaShawn Keirsey Jr.": 680577,
  "Danny Coulombe": 543056,
  "David Festa": 701581,
  "Griffin Jax": 643377,
  "Harrison Bader": 664056,
  "Jhoan Duran": 661395,
  "Joe Ryan": 657746,
  "Joey Wentz": 666214,
  "Jonah Bride": 681146,
  "Justin Topa": 623437,
  "Kody Clemens": 665019,
  "Louis Varland": 686973,
  "Matt Wallner": 670242,
  "Ryan Jeffers": 680777,
  "Simeon Woods Richardson": 680573,
  "Trevor Larnach": 663616,
  "Ty France": 664034,
  "Willi Castro": 650489,
  "Alan Rangel": 660604,
  "Alec Bohm": 664761,
  "Brandon Marsh": 669016,
  "Bryson Stott": 681082,
  "Buddy Kennedy": 671083,
  "Cristopher S\u00e1nchez": 650911,
  "Edmundo Sosa": 624641,
  "J.T. Realmuto": 592663,
  "Jes\u00fas Luzardo": 666200,
  "Joe Ross": 605452,
  "Johan Rojas": 679032,
  "Jordan Romano": 605447,
  "Kyle Schwarber": 656941,
  "Matt Strahm": 621381,
  "Max Kepler": 596146,
  "Max Lazar": 676661,
  "Mick Abel": 690953,
  "Nick Castellanos": 592206,
  "Orion Kerkering": 689147,
  "Otto Kemp": 805249,
  "Rafael March\u00e1n": 665561,
  "Ranger Su\u00e1rez": 624133,
  "Taijuan Walker": 592836,
  "Tanner Banks": 621383,
  "Trea Turner": 607208,
  "Zack Wheeler": 554430,
  "Aaron Bummer": 607481,
  "Alex Verdugo": 657077,
  "Austin Cox": 680735,
  "Austin Riley": 663586,
  "Bryce Elder": 693821,
  "Didier Fuentes": 800311,
  "Drake Baldwin": 686948,
  "Dylan Dodd": 689266,
  "Dylan Lee": 669276,
  "Eli White": 642201,
  "Enyel De Los Santos": 660853,
  "Grant Holmes": 656550,
  "Luke Williams": 663897,
  "Marcell Ozuna": 542303,
  "Matt Olson": 621566,
  "Michael Harris II": 671739,
  "Nick Allen": 669397,
  "Ozzie Albies": 645277,
  "Pierce Johnson": 572955,
  "Rafael Montero": 606160,
  "Raisel Iglesias": 628452,
  "Ronald Acu\u00f1a Jr.": 660670,
  "Sean Murphy": 669221,
  "Spencer Schwellenbach": 680885,
  "Spencer Strider": 675911,
  "Stuart Fairchild": 656413,
  "Aaron Civale": 650644,
  "Adrian Houser": 605288,
  "Andrew Benintendi": 643217,
  "Austin Slater": 596103,
  "Brandon Eisert": 685126,
  "Chase Meidroth": 805367,
  "Dan Altavilla": 656186,
  "Edgar Quero": 700337,
  "Grant Taylor": 691799,
  "Jordan Leasure": 673929,
  "Josh Rojas": 668942,
  "Kyle Teel": 691019,
  "Lenyn Sosa": 672820,
  "Luis Robert Jr.": 673357,
  "Michael A. Taylor": 572191,
  "Miguel Vargas": 678246,
  "Mike Tauchman": 643565,
  "Mike Vasil": 678024,
  "Ryan Noda": 676116,
  "Sean Burke": 680732,
  "Shane Smith": 681343,
  "Steven Wilson": 621051,
  "Tyler Alexander": 641302,
  "Tyler Gilbert": 656457,
  "Vinny Capra": 681962,
  "Wikelman Gonz\u00e1lez": 682790,
  "Agust\u00edn Ram\u00edrez": 682663,
  "Anthony Bender": 669622,
  "Cade Gibson": 806188,
  "Cal Quantrill": 615698,
  "Calvin Faucher": 676534,
  "Connor Norby": 681393,
  "Dane Myers": 667472,
  "Edward Cabrera": 665795,
  "Eric Wagaman": 676572,
  "Eury P\u00e9rez": 691587,
  "Heriberto Hernandez": 681715,
  "Jack Winkler": 676466,
  "Janson Junk": 676083,
  "Javier Sanoja": 691594,
  "Jes\u00fas S\u00e1nchez": 660821,
  "Josh Simpson": 681006,
  "Kyle Stowers": 669065,
  "Lake Bachar": 669199,
  "Liam Hicks": 689414,
  "Nick Fortes": 663743,
  "Otto Lopez": 672640,
  "Ronny Henriquez": 678692,
  "Sandy Alcantara": 645261,
  "Tyler Phillips": 663969,
  "Valente Bellozo": 678368,
  "Xavier Edwards": 669364,
  "Aaron Judge": 592450,
  "Allan Winans": 642216,
  "Anthony Volpe": 683011,
  "Austin Wells": 669224,
  "Ben Rice": 700250,
  "Carlos Rod\u00f3n": 607074,
  "Clarke Schmidt": 657376,
  "Cody Bellinger": 641355,
  "DJ LeMahieu": 518934,
  "Devin Williams": 642207,
  "Fernando Cruz": 518585,
  "Giancarlo Stanton": 519317,
  "Ian Hamilton": 641656,
  "J.C. Escarra": 641555,
  "JT Brubaker": 664141,
  "Jasson Dom\u00ednguez": 691176,
  "Jazz Chisholm Jr.": 665862,
  "Jonathan Lo\u00e1isiga": 642528,
  "Luke Weaver": 596133,
  "Mark Leiter Jr.": 643410,
  "Max Fried": 608331,
  "Oswald Peraza": 672724,
  "Paul Goldschmidt": 502671,
  "Tim Hill": 657612,
  "Trent Grisham": 663757,
  "Will Warren": 701542,
  "Aaron Ashby": 676879,
  "Abner Uribe": 682842,
  "Andruw Monasterio": 655316,
  "Brice Turang": 668930,
  "Caleb Durbin": 702332,
  "Chad Patrick": 694477,
  "Christian Yelich": 592885,
  "DL Hall": 669084,
  "Daz Cameron": 663662,
  "Eric Haase": 606992,
  "Freddy Peralta": 642547,
  "Grant Anderson": 681982,
  "Isaac Collins": 686555,
  "Jackson Chourio": 694192,
  "Jacob Misiorowski": 694819,
  "Jake Bauers": 641343,
  "Jared Koenig": 657649,
  "Joey Ortiz": 687401,
  "Jose Quintana": 500779,
  "Nick Mears": 683232,
  "Quinn Priester": 682990,
  "Rhys Hoskins": 656555,
  "Rob Zastryzny": 642239,
  "Sal Frelick": 686217,
  "Trevor Megill": 656730,
  "William Contreras": 661388
}