{
  "commands": [
    {
      "name": "pick",
      "description": "Analyze a bet slip and provide structured betting analysis",
      "options": [
        {
          "name": "channel_type",
          "description": "Type of betting play to post",
          "type": "STRING",
          "required": true,
          "choices": [
            {
              "name": "VIP Play",
              "value": "vip_plays"
            },
            {
              "name": "Free Play",
              "value": "free_plays"
            },
            {
              "name": "Lotto Ticket",
              "value": "lotto_ticket"
            }
          ]
        },
        {
          "name": "image",
          "description": "Bet slip image to analyze",
          "type": "ATTACHMENT",
          "required": true
        },
        {
          "name": "units",
          "description": "Units for VIP plays (e.g., 2u, 1.5u) - only used for VIP plays",
          "type": "STRING",
          "required": false
        },
        {
          "name": "debug",
          "description": "Enable debug mode for OCR analysis (saves debug images)",
          "type": "BOOLEAN",
          "required": false
        }
      ]
    },
    {
      "name": "admin",
      "description": "Admin commands",
      "options": [
        {
          "name": "ping",
          "description": "Test bot responsiveness",
          "type": "SUB_COMMAND",
          "required": true
        },
        {
          "name": "status",
          "description": "Check bot and system status",
          "type": "SUB_COMMAND",
          "required": true
        }
      ]
    }
  ]
} 